animec/__init__.py
animec/anicore.py
animec/aninews.py
animec/errors.py
animec/helpers.py
animec/sagasu.py
animec/waifu.py
animec-0.4.2.dist-info/LICENSE.txt
animec-0.4.2.dist-info/METADATA
animec-0.4.2.dist-info/WHEEL
animec-0.4.2.dist-info/top_level.txt
animec-0.4.2.dist-info/RECORD
