Metadata-Version: 2.1
Name: animec
Version: 0.4.2
Summary: A module to get data about anime characters, news, info, lyrics and more.
Home-page: https://github.com/DriftAsimov/animec
Author: DriftAsimov
Author-email: driftasimov@gmail.com
License: MIT
Project-URL: Documentation, https://animec.readthedocs.io/en/latest/
Project-URL: Issue tracker, https://github.com/DriftAsimov/animec/issues
Project-URL: Github, https://github.com/DriftAsimov/animec
Keywords: animecharacter anime character myanimelist news animenews animeinfo music animelyrics lyrics
Platform: UNKNOWN
Classifier: Development Status :: 5 - Production/Stable
Classifier: Intended Audience :: Developers
Classifier: Operating System :: OS Independent
Classifier: License :: OSI Approved :: MIT License
Classifier: Programming Language :: Python :: 3
Classifier: Topic :: Education :: Testing
Classifier: Topic :: Software Development :: Libraries
License-File: LICENSE.txt
Requires-Dist: bs4 (>=0.0.1)
Requires-Dist: urllib3 (>=1.25.9)
